chaptermarkers/__init__.py
chaptermarkers/chaptermarkers.py
chaptermarkers-1.2.8.dist-info/AUTHORS.rst
chaptermarkers-1.2.8.dist-info/LICENSE.rst
chaptermarkers-1.2.8.dist-info/METADATA
chaptermarkers-1.2.8.dist-info/WHEEL
chaptermarkers-1.2.8.dist-info/entry_points.txt
chaptermarkers-1.2.8.dist-info/top_level.txt
chaptermarkers-1.2.8.dist-info/RECORD
