Metadata-Version: 2.1
Name: chaptermarkers
Version: 1.2.8
Summary: chaptermarkers writes markers to MP4 files.
Home-page: https://github.com/cbitterfield/chaptermarkers.git
Author: Colin Bitterfield
Author-email: cbitterfield@gmail.com
License: MIT license
Platform: UNKNOWN
Classifier: Development Status :: 4 - Beta
Classifier: Intended Audience :: Developers
Classifier: License :: OSI Approved :: MIT License
Classifier: Natural Language :: English
Classifier: Programming Language :: Python :: 3
Classifier: Programming Language :: Python :: 3.6
Classifier: Programming Language :: Python :: 3.7
Classifier: Programming Language :: Python :: 3.8
Classifier: Programming Language :: Python :: 3.9
Classifier: Environment :: Console
Classifier: Topic :: Software Development :: Libraries :: Python Modules
Requires-Python: >=3
